LICENSE
MANIFEST.in
README.rst
setup.cfg
setup.py
arbalest/__init__.py
arbalest/configuration.py
arbalest/core.py
arbalest/s3.py
arbalest/sql.py
arbalest.egg-info/PKG-INFO
arbalest.egg-info/SOURCES.txt
arbalest.egg-info/dependency_links.txt
arbalest.egg-info/requires.txt
arbalest.egg-info/top_level.txt
arbalest/contrib/__init__.py
arbalest/contrib/luigi.py
arbalest/pipeline/__init__.py
arbalest/redshift/__init__.py
arbalest/redshift/manifest.py
arbalest/redshift/runner.py
arbalest/redshift/schema.py
arbalest/redshift/step.py