Metadata-Version: 1.1
Name: arbalest
Version: 1.6.2
Summary: Arbalest orchestrates bulk data loading for Amazon Redshift
Home-page: https://github.com/Dwolla/arbalest
Author: Fredrick Galoso
Author-email: fred+arbalest@dwolla.com
License: MIT
Platform: UNKNOWN
Classifier: Development Status :: 5 - Production/Stable
Classifier: Intended Audience :: Developers
Classifier: License :: OSI Approved :: MIT License
Classifier: Natural Language :: English
Classifier: Operating System :: OS Independent
Classifier: Programming Language :: Python
Classifier: Programming Language :: Python :: 2
Classifier: Programming Language :: Python :: 2.6
Classifier: Programming Language :: Python :: 2.7
Classifier: Topic :: Database :: Database Engines/Servers
Classifier: Topic :: System :: Distributed Computing
